simple_leftrefill_inpainting/LeftRefill/LICENSE
simple_leftrefill_inpainting/LeftRefill/README.md
simple_leftrefill_inpainting/LeftRefill/check_points/ref_guided_inpainting/ckpts/epoch=7-step=6039.ckpt
simple_leftrefill_inpainting/LeftRefill/check_points/ref_guided_inpainting/model_config.yaml
simple_leftrefill_inpainting/LeftRefill/check_points/ref_guided_inpainting/training_config.yaml
simple_leftrefill_inpainting/LeftRefill/configs/multiview_ref_inpainting.yaml
simple_leftrefill_inpainting/LeftRefill/configs/multiview_ref_inpainting_training_config.yaml
simple_leftrefill_inpainting/LeftRefill/configs/novel_view_synthesis.yaml
simple_leftrefill_inpainting/LeftRefill/configs/nvs_training_config.yaml
simple_leftrefill_inpainting/LeftRefill/configs/ref_inpainting.yaml
simple_leftrefill_inpainting/LeftRefill/configs/ref_inpainting_training_config.yaml
simple_leftrefill_inpainting/LeftRefill/dataloaders/inpainting_crossview_dataset.py
simple_leftrefill_inpainting/LeftRefill/dataloaders/inpainting_dataset.py
simple_leftrefill_inpainting/LeftRefill/dataloaders/obj_nvs_dataset.py
simple_leftrefill_inpainting/LeftRefill/dataloaders/test_dataset.py
simple_leftrefill_inpainting/LeftRefill/extend_data_for_multiview.py
simple_leftrefill_inpainting/LeftRefill/inpainting_ldm/NVS_ldm.py
simple_leftrefill_inpainting/LeftRefill/inpainting_ldm/logger.py
simple_leftrefill_inpainting/LeftRefill/inpainting_ldm/lora.py
simple_leftrefill_inpainting/LeftRefill/inpainting_ldm/model.py
simple_leftrefill_inpainting/LeftRefill/inpainting_ldm/multiview_ref_inpainting_ldm.py
simple_leftrefill_inpainting/LeftRefill/inpainting_ldm/ref_inpainting_ldm.py
simple_leftrefill_inpainting/LeftRefill/inpainting_ldm/safe_open.py
simple_leftrefill_inpainting/LeftRefill/ldm/models/autoencoder.py
simple_leftrefill_inpainting/LeftRefill/ldm/models/diffusion/__init__.py
simple_leftrefill_inpainting/LeftRefill/ldm/models/diffusion/ddim.py
simple_leftrefill_inpainting/LeftRefill/ldm/models/diffusion/ddpm.py
simple_leftrefill_inpainting-0.0.1.dist-info/LICENSE
simple_leftrefill_inpainting-0.0.1.dist-info/METADATA
simple_leftrefill_inpainting-0.0.1.dist-info/WHEEL
simple_leftrefill_inpainting-0.0.1.dist-info/entry_points.txt
simple_leftrefill_inpainting-0.0.1.dist-info/RECORD
