Metadata-Version: 2.1
Name: simple-leftrefill-inpainting
Version: 0.0.1
Summary: This is a wrapper api of paper LeftRefill
Author: jingwei xu
Author-email: davidxujw@gmail.com
Requires-Python: >=3.10,<4.0
Classifier: Programming Language :: Python :: 3
Classifier: Programming Language :: Python :: 3.10
Classifier: Programming Language :: Python :: 3.11
Classifier: Programming Language :: Python :: 3.12
Classifier: Programming Language :: Python :: 3.13
Requires-Dist: diffusers (==0.27.2)
Requires-Dist: easydict
Requires-Dist: einops
Requires-Dist: fire (>=0.5.0,<0.6.0)
Requires-Dist: huggingface_hub (==0.20.2)
Requires-Dist: kornia (==0.5.0)
Requires-Dist: numpy (>=1.24.3,<2.0.0)
Requires-Dist: omegaconf
Requires-Dist: open_clip_torch (==2.16.0)
Requires-Dist: opencv-python (>=4.8.0.74,<5.0.0.0)
Requires-Dist: pillow (>=9.5.0,<10.0.0)
Requires-Dist: pytorch_lightning (==1.5.0)
Requires-Dist: scikit-image
Requires-Dist: timm (==0.4.12)
Requires-Dist: torch (>=1.13.1,!=2.0.1)
Requires-Dist: torchvision (>=0.14.1)
Requires-Dist: transformers (==4.39.3)
Requires-Dist: webdataset
Requires-Dist: yacs (==0.1.8)
